{
  "name": "furkies-purrkies-poetry-0317",
  "title": "One",
  "date": "2021-01-12T03:57:33.086Z",
  "image": "poetry-0317-illustration.jpg",
  "audio": "poetry-0317.mp3",
  "artwork": "https://unsplash.com/photos/ZNz5UPRb2N8",
  "id": "furkies-purrkies-poetry-0317",
  "attachments": {},
  "html": "<div class=\"section\">\n  <p>Use wisdom,</p>\n  <p>Get ahead of trouble.</p>\n</div>\n\n<div class=\"section\">\n  <p>Find them,</p>\n  <p>find all your ends.</p>\n</div>\n\n<div class=\"section\">\n  <p>Bring them within,</p>\n  <p>make a start.</p>\n</div>\n\n<div class=\"section\">\n  <p>We do not age,</p>\n  <p>we amplify.</p>\n</div>\n\n<div class=\"section\">\n  <p>Don&apos;t stop,</p>\n  <p>align in balance.</p>\n</div>\n\n<div class=\"section\">\n  <p>The slightest push,</p>\n  <p>is the greatest force.</p>\n</div>\n\n<div class=\"section\">\n  <hr>\n</div>\n\n<div class=\"section\">\n  <p>You cannot grow,</p>\n  <p>without a multiplex.</p>\n</div>\n\n<div class=\"section\">\n  <p>One thousand,</p>\n  <p>little audio books.</p>\n</div>\n\n<div class=\"section\">\n  <p>One thousand lives,</p>\n  <p>to power your start.</p>\n</div>\n\n<div class=\"section\">\n  <p>Quickening worthy,</p>\n  <p>of gods and royalty.</p>\n</div>\n\n<div class=\"section\">\n  <p>We are unbreakable,</p>\n  <p>we are truly, Unimaginable.</p>\n</div>\n\n<div class=\"section\">\n  <hr>\n</div>\n\n<div class=\"section\">\n  <p>As flowers need water.</p>\n  <p>we need books.</p>\n</div>\n\n<div class=\"section\">\n  <p>We have minds,</p>\n  <p>and those must grow.</p>\n</div>\n\n<div class=\"section\">\n  <p>Don&apos;t listen to anybody,</p>\n  <p>they are not enough.</p>\n</div>\n\n<div class=\"section\">\n  <p>You need,</p>\n  <p>a thousand voices.</p>\n</div>\n\n<div class=\"section\">\n  <p>A thousand,</p>\n  <p>lifetimes.</p>\n</div>\n\n<div class=\"section\">\n  <hr>\n</div>\n\n<div class=\"section\">\n  <p>Flowers,</p>\n  <p>need light to bloom.</p>\n</div>\n\n<div class=\"section\">\n  <p>Our minds need,</p>\n  <p>a thousand lifetimes.</p>\n</div>\n\n<div class=\"section\">\n  <p>In darkness,</p>\n  <p>nothing can bloom.</p>\n</div>\n\n<div class=\"section\">\n  <p>The curse was never knowing,</p>\n  <p>that you were to bloom.</p>\n</div>\n\n<div class=\"section\">\n  <p>One Thousand Books,</p>\n  <p>and the curse is broken now.</p>\n</div>\n\n<div class=\"section\">\n  <hr>\n</div>\n\n<div class=\"section\">\n  <p>Do not be scared,</p>\n  <p>wisdom is safety.</p>\n</div>\n\n<div class=\"section\">\n  <p>Do not be worried,</p>\n  <p>Humanity grows with you.</p>\n</div>\n\n<div class=\"section\">\n  <p>One for all,</p>\n  <p>and all of one.</p>\n</div>\n\n<div class=\"section\">\n  <p>Let the nature trails,</p>\n  <p>bring you moon and sun.</p>\n</div>\n\n<div class=\"section\">\n  <p>Slow down and listen,</p>\n  <p>let the narrators read.</p>\n</div>\n\n<div class=\"section\">\n  <p>Let a thousand wise beings</p>\n  <p>speak to you as one.</p>\n</div>",
  "bootstrap": "<div class=\"card card-section bg-dark text-warning shadow\">\n  <div class=\"section card-body mb-0 my-2\">\n    <div class=\"paragraph card-text card-stanza my-5 text-center\">Use wisdom,</div>\n    <div class=\"paragraph card-text card-stanza my-5 text-center\">Get ahead of trouble.</div>\n  </div>\n</div>\n<div class=\"card card-section bg-dark text-warning shadow\">\n  <div class=\"section card-body mb-0 my-2\">\n    <div class=\"paragraph card-text card-stanza my-5 text-center\">Find them,</div>\n    <div class=\"paragraph card-text card-stanza my-5 text-center\">find all your ends.</div>\n  </div>\n</div>\n<div class=\"card card-section bg-dark text-warning shadow\">\n  <div class=\"section card-body mb-0 my-2\">\n    <div class=\"paragraph card-text card-stanza my-5 text-center\">Bring them within,</div>\n    <div class=\"paragraph card-text card-stanza my-5 text-center\">make a start.</div>\n  </div>\n</div>\n<div class=\"card card-section bg-dark text-warning shadow\">\n  <div class=\"section card-body mb-0 my-2\">\n    <div class=\"paragraph card-text card-stanza my-5 text-center\">We do not age,</div>\n    <div class=\"paragraph card-text card-stanza my-5 text-center\">we amplify.</div>\n  </div>\n</div>\n<div class=\"card card-section bg-dark text-warning shadow\">\n  <div class=\"section card-body mb-0 my-2\">\n    <div class=\"paragraph card-text card-stanza my-5 text-center\">Don't stop,</div>\n    <div class=\"paragraph card-text card-stanza my-5 text-center\">align in balance.</div>\n  </div>\n</div>\n<div class=\"card card-section bg-dark text-warning shadow\">\n  <div class=\"section card-body mb-0 my-2\">\n    <div class=\"paragraph card-text card-stanza my-5 text-center\">The slightest push,</div>\n    <div class=\"paragraph card-text card-stanza my-5 text-center\">is the greatest force.</div>\n  </div>\n</div>\n<div class=\"mb-5 section-spacer\">&nbsp;</div>\n<div class=\"card card-section bg-dark text-warning shadow\">\n  <div class=\"section card-body mb-0 my-2\">\n    <div class=\"paragraph card-text card-stanza my-5 text-center\">You cannot grow,</div>\n    <div class=\"paragraph card-text card-stanza my-5 text-center\">without a multiplex.</div>\n  </div>\n</div>\n<div class=\"card card-section bg-dark text-warning shadow\">\n  <div class=\"section card-body mb-0 my-2\">\n    <div class=\"paragraph card-text card-stanza my-5 text-center\">One thousand,</div>\n    <div class=\"paragraph card-text card-stanza my-5 text-center\">little audio books.</div>\n  </div>\n</div>\n<div class=\"card card-section bg-dark text-warning shadow\">\n  <div class=\"section card-body mb-0 my-2\">\n    <div class=\"paragraph card-text card-stanza my-5 text-center\">One thousand lives,</div>\n    <div class=\"paragraph card-text card-stanza my-5 text-center\">to power your start.</div>\n  </div>\n</div>\n<div class=\"card card-section bg-dark text-warning shadow\">\n  <div class=\"section card-body mb-0 my-2\">\n    <div class=\"paragraph card-text card-stanza my-5 text-center\">Quickening worthy,</div>\n    <div class=\"paragraph card-text card-stanza my-5 text-center\">of gods and royalty.</div>\n  </div>\n</div>\n<div class=\"card card-section bg-dark text-warning shadow\">\n  <div class=\"section card-body mb-0 my-2\">\n    <div class=\"paragraph card-text card-stanza my-5 text-center\">We are unbreakable,</div>\n    <div class=\"paragraph card-text card-stanza my-5 text-center\">we are truly, Unimaginable.</div>\n  </div>\n</div>\n<div class=\"mb-5 section-spacer\">&nbsp;</div>\n<div class=\"card card-section bg-dark text-warning shadow\">\n  <div class=\"section card-body mb-0 my-2\">\n    <div class=\"paragraph card-text card-stanza my-5 text-center\">As flowers need water.</div>\n    <div class=\"paragraph card-text card-stanza my-5 text-center\">we need books.</div>\n  </div>\n</div>\n<div class=\"card card-section bg-dark text-warning shadow\">\n  <div class=\"section card-body mb-0 my-2\">\n    <div class=\"paragraph card-text card-stanza my-5 text-center\">We have minds,</div>\n    <div class=\"paragraph card-text card-stanza my-5 text-center\">and those must grow.</div>\n  </div>\n</div>\n<div class=\"card card-section bg-dark text-warning shadow\">\n  <div class=\"section card-body mb-0 my-2\">\n    <div class=\"paragraph card-text card-stanza my-5 text-center\">Don't listen to anybody,</div>\n    <div class=\"paragraph card-text card-stanza my-5 text-center\">they are not enough.</div>\n  </div>\n</div>\n<div class=\"card card-section bg-dark text-warning shadow\">\n  <div class=\"section card-body mb-0 my-2\">\n    <div class=\"paragraph card-text card-stanza my-5 text-center\">You need,</div>\n    <div class=\"paragraph card-text card-stanza my-5 text-center\">a thousand voices.</div>\n  </div>\n</div>\n<div class=\"card card-section bg-dark text-warning shadow\">\n  <div class=\"section card-body mb-0 my-2\">\n    <div class=\"paragraph card-text card-stanza my-5 text-center\">A thousand,</div>\n    <div class=\"paragraph card-text card-stanza my-5 text-center\">lifetimes.</div>\n  </div>\n</div>\n<div class=\"mb-5 section-spacer\">&nbsp;</div>\n<div class=\"card card-section bg-dark text-warning shadow\">\n  <div class=\"section card-body mb-0 my-2\">\n    <div class=\"paragraph card-text card-stanza my-5 text-center\">Flowers,</div>\n    <div class=\"paragraph card-text card-stanza my-5 text-center\">need light to bloom.</div>\n  </div>\n</div>\n<div class=\"card card-section bg-dark text-warning shadow\">\n  <div class=\"section card-body mb-0 my-2\">\n    <div class=\"paragraph card-text card-stanza my-5 text-center\">Our minds need,</div>\n    <div class=\"paragraph card-text card-stanza my-5 text-center\">a thousand lifetimes.</div>\n  </div>\n</div>\n<div class=\"card card-section bg-dark text-warning shadow\">\n  <div class=\"section card-body mb-0 my-2\">\n    <div class=\"paragraph card-text card-stanza my-5 text-center\">In darkness,</div>\n    <div class=\"paragraph card-text card-stanza my-5 text-center\">nothing can bloom.</div>\n  </div>\n</div>\n<div class=\"card card-section bg-dark text-warning shadow\">\n  <div class=\"section card-body mb-0 my-2\">\n    <div class=\"paragraph card-text card-stanza my-5 text-center\">The curse was never knowing,</div>\n    <div class=\"paragraph card-text card-stanza my-5 text-center\">that you were to bloom.</div>\n  </div>\n</div>\n<div class=\"card card-section bg-dark text-warning shadow\">\n  <div class=\"section card-body mb-0 my-2\">\n    <div class=\"paragraph card-text card-stanza my-5 text-center\">One Thousand Books,</div>\n    <div class=\"paragraph card-text card-stanza my-5 text-center\">and the curse is broken now.</div>\n  </div>\n</div>\n<div class=\"mb-5 section-spacer\">&nbsp;</div>\n<div class=\"card card-section bg-dark text-warning shadow\">\n  <div class=\"section card-body mb-0 my-2\">\n    <div class=\"paragraph card-text card-stanza my-5 text-center\">Do not be scared,</div>\n    <div class=\"paragraph card-text card-stanza my-5 text-center\">wisdom is safety.</div>\n  </div>\n</div>\n<div class=\"card card-section bg-dark text-warning shadow\">\n  <div class=\"section card-body mb-0 my-2\">\n    <div class=\"paragraph card-text card-stanza my-5 text-center\">Do not be worried,</div>\n    <div class=\"paragraph card-text card-stanza my-5 text-center\">Humanity grows with you.</div>\n  </div>\n</div>\n<div class=\"card card-section bg-dark text-warning shadow\">\n  <div class=\"section card-body mb-0 my-2\">\n    <div class=\"paragraph card-text card-stanza my-5 text-center\">One for all,</div>\n    <div class=\"paragraph card-text card-stanza my-5 text-center\">and all of one.</div>\n  </div>\n</div>\n<div class=\"card card-section bg-dark text-warning shadow\">\n  <div class=\"section card-body mb-0 my-2\">\n    <div class=\"paragraph card-text card-stanza my-5 text-center\">Let the nature trails,</div>\n    <div class=\"paragraph card-text card-stanza my-5 text-center\">bring you moon and sun.</div>\n  </div>\n</div>\n<div class=\"card card-section bg-dark text-warning shadow\">\n  <div class=\"section card-body mb-0 my-2\">\n    <div class=\"paragraph card-text card-stanza my-5 text-center\">Slow down and listen,</div>\n    <div class=\"paragraph card-text card-stanza my-5 text-center\">let the narrators read.</div>\n  </div>\n</div>\n<div class=\"card card-section bg-dark text-warning shadow\">\n  <div class=\"section card-body mb-0 my-2\">\n    <div class=\"paragraph card-text card-stanza my-5 text-center\">Let a thousand wise beings</div>\n    <div class=\"paragraph card-text card-stanza my-5 text-center\">speak to you as one.</div>\n  </div>\n</div>",
  "print": "<div class=\"section avoid-break-inside\" style=\"padding-bottom: 2rem;\">\n  <div class=\"paragraph\">Use wisdom,</div>\n  <div class=\"paragraph\">Get ahead of trouble.</div>\n</div>\n<div class=\"section avoid-break-inside\" style=\"padding-bottom: 2rem;\">\n  <div class=\"paragraph\">Find them,</div>\n  <div class=\"paragraph\">find all your ends.</div>\n</div>\n<div class=\"section avoid-break-inside\" style=\"padding-bottom: 2rem;\">\n  <div class=\"paragraph\">Bring them within,</div>\n  <div class=\"paragraph\">make a start.</div>\n</div>\n<div class=\"section avoid-break-inside\" style=\"padding-bottom: 2rem;\">\n  <div class=\"paragraph\">We do not age,</div>\n  <div class=\"paragraph\">we amplify.</div>\n</div>\n<div class=\"section avoid-break-inside\" style=\"padding-bottom: 2rem;\">\n  <div class=\"paragraph\">Don't stop,</div>\n  <div class=\"paragraph\">align in balance.</div>\n</div>\n<div class=\"section avoid-break-inside\" style=\"padding-bottom: 2rem;\">\n  <div class=\"paragraph\">The slightest push,</div>\n  <div class=\"paragraph\">is the greatest force.</div>\n</div>\n<div class=\"section avoid-break-inside\" style=\"padding-bottom: 2rem;\">\n  <br>\n</div>\n<div class=\"section avoid-break-inside\" style=\"padding-bottom: 2rem;\">\n  <div class=\"paragraph\">You cannot grow,</div>\n  <div class=\"paragraph\">without a multiplex.</div>\n</div>\n<div class=\"section avoid-break-inside\" style=\"padding-bottom: 2rem;\">\n  <div class=\"paragraph\">One thousand,</div>\n  <div class=\"paragraph\">little audio books.</div>\n</div>\n<div class=\"section avoid-break-inside\" style=\"padding-bottom: 2rem;\">\n  <div class=\"paragraph\">One thousand lives,</div>\n  <div class=\"paragraph\">to power your start.</div>\n</div>\n<div class=\"section avoid-break-inside\" style=\"padding-bottom: 2rem;\">\n  <div class=\"paragraph\">Quickening worthy,</div>\n  <div class=\"paragraph\">of gods and royalty.</div>\n</div>\n<div class=\"section avoid-break-inside\" style=\"padding-bottom: 2rem;\">\n  <div class=\"paragraph\">We are unbreakable,</div>\n  <div class=\"paragraph\">we are truly, Unimaginable.</div>\n</div>\n<div class=\"section avoid-break-inside\" style=\"padding-bottom: 2rem;\">\n  <br>\n</div>\n<div class=\"section avoid-break-inside\" style=\"padding-bottom: 2rem;\">\n  <div class=\"paragraph\">As flowers need water.</div>\n  <div class=\"paragraph\">we need books.</div>\n</div>\n<div class=\"section avoid-break-inside\" style=\"padding-bottom: 2rem;\">\n  <div class=\"paragraph\">We have minds,</div>\n  <div class=\"paragraph\">and those must grow.</div>\n</div>\n<div class=\"section avoid-break-inside\" style=\"padding-bottom: 2rem;\">\n  <div class=\"paragraph\">Don't listen to anybody,</div>\n  <div class=\"paragraph\">they are not enough.</div>\n</div>\n<div class=\"section avoid-break-inside\" style=\"padding-bottom: 2rem;\">\n  <div class=\"paragraph\">You need,</div>\n  <div class=\"paragraph\">a thousand voices.</div>\n</div>\n<div class=\"section avoid-break-inside\" style=\"padding-bottom: 2rem;\">\n  <div class=\"paragraph\">A thousand,</div>\n  <div class=\"paragraph\">lifetimes.</div>\n</div>\n<div class=\"section avoid-break-inside\" style=\"padding-bottom: 2rem;\">\n  <br>\n</div>\n<div class=\"section avoid-break-inside\" style=\"padding-bottom: 2rem;\">\n  <div class=\"paragraph\">Flowers,</div>\n  <div class=\"paragraph\">need light to bloom.</div>\n</div>\n<div class=\"section avoid-break-inside\" style=\"padding-bottom: 2rem;\">\n  <div class=\"paragraph\">Our minds need,</div>\n  <div class=\"paragraph\">a thousand lifetimes.</div>\n</div>\n<div class=\"section avoid-break-inside\" style=\"padding-bottom: 2rem;\">\n  <div class=\"paragraph\">In darkness,</div>\n  <div class=\"paragraph\">nothing can bloom.</div>\n</div>\n<div class=\"section avoid-break-inside\" style=\"padding-bottom: 2rem;\">\n  <div class=\"paragraph\">The curse was never knowing,</div>\n  <div class=\"paragraph\">that you were to bloom.</div>\n</div>\n<div class=\"section avoid-break-inside\" style=\"padding-bottom: 2rem;\">\n  <div class=\"paragraph\">One Thousand Books,</div>\n  <div class=\"paragraph\">and the curse is broken now.</div>\n</div>\n<div class=\"section avoid-break-inside\" style=\"padding-bottom: 2rem;\">\n  <br>\n</div>\n<div class=\"section avoid-break-inside\" style=\"padding-bottom: 2rem;\">\n  <div class=\"paragraph\">Do not be scared,</div>\n  <div class=\"paragraph\">wisdom is safety.</div>\n</div>\n<div class=\"section avoid-break-inside\" style=\"padding-bottom: 2rem;\">\n  <div class=\"paragraph\">Do not be worried,</div>\n  <div class=\"paragraph\">Humanity grows with you.</div>\n</div>\n<div class=\"section avoid-break-inside\" style=\"padding-bottom: 2rem;\">\n  <div class=\"paragraph\">One for all,</div>\n  <div class=\"paragraph\">and all of one.</div>\n</div>\n<div class=\"section avoid-break-inside\" style=\"padding-bottom: 2rem;\">\n  <div class=\"paragraph\">Let the nature trails,</div>\n  <div class=\"paragraph\">bring you moon and sun.</div>\n</div>\n<div class=\"section avoid-break-inside\" style=\"padding-bottom: 2rem;\">\n  <div class=\"paragraph\">Slow down and listen,</div>\n  <div class=\"paragraph\">let the narrators read.</div>\n</div>\n<div class=\"section avoid-break-inside\" style=\"padding-bottom: 2rem;\">\n  <div class=\"paragraph\">Let a thousand wise beings</div>\n  <div class=\"paragraph\">speak to you as one.</div>\n</div>",
  "text": "Use wisdom,\nGet ahead of trouble.\n\nFind them,\nfind all your ends.\n\nBring them within,\nmake a start.\n\nWe do not age,\nwe amplify.\n\nDon't stop,\nalign in balance.\n\nThe slightest push,\nis the greatest force.\n\nYou cannot grow,\nwithout a multiplex.\n\nOne thousand,\nlittle audio books.\n\nOne thousand lives,\nto power your start.\n\nQuickening worthy,\nof gods and royalty.\n\nWe are unbreakable,\nwe are truly, Unimaginable.\n\nAs flowers need water.\nwe need books.\n\nWe have minds,\nand those must grow.\n\nDon't listen to anybody,\nthey are not enough.\n\nYou need,\na thousand voices.\n\nA thousand,\nlifetimes.\n\nFlowers,\nneed light to bloom.\n\nOur minds need,\na thousand lifetimes.\n\nIn darkness,\nnothing can bloom.\n\nThe curse was never knowing,\nthat you were to bloom.\n\nOne Thousand Books,\nand the curse is broken now.\n\nDo not be scared,\nwisdom is safety.\n\nDo not be worried,\nHumanity grows with you.\n\nOne for all,\nand all of one.\n\nLet the nature trails,\nbring you moon and sun.\n\nSlow down and listen,\nlet the narrators read.\n\nLet a thousand wise beings\nspeak to you as one.",
  "images": [],
  "links": []
}