{
  "name": "furkies-purrkies-poetry-0017",
  "title": "The Birds Are Going Wild Outside My Window",
  "date": "2020-03-29T11:14:44.761Z",
  "image": "poetry-0017-illustration.jpg",
  "artwork": "https://catpea.com/",
  "id": "furkies-purrkies-poetry-0017",
  "attachments": {},
  "html": "<div class=\"section\">\n  <p>The birds are going wild outside my window.</p>\n</div>\n<div class=\"section\">\n  <p>Probably because of all the Plump Squirrels I&apos;ve been feeding.</p>\n</div>\n<div class=\"section\">\n  <p>Dammit.</p>\n</div>",
  "bootstrap": "<div class=\"card card-section bg-dark text-warning shadow\">\n  <div class=\"section card-body mb-0 my-2\">\n    <div class=\"paragraph card-text card-stanza my-5 text-center\">The birds are going wild outside my window.</div>\n  </div>\n</div>\n<div class=\"card card-section bg-dark text-warning shadow\">\n  <div class=\"section card-body mb-0 my-2\">\n    <div class=\"paragraph card-text card-stanza my-5 text-center\">Probably because of all the Plump Squirrels I've been feeding.</div>\n  </div>\n</div>\n<div class=\"card card-section bg-dark text-warning shadow\">\n  <div class=\"section card-body mb-0 my-2\">\n    <div class=\"paragraph card-text card-stanza my-5 text-center\">Dammit.</div>\n  </div>\n</div>",
  "print": "<div class=\"section avoid-break-inside\" style=\"padding-bottom: 2rem;\">\n  <div class=\"paragraph\">The birds are going wild outside my window.</div>\n</div>\n<div class=\"section avoid-break-inside\" style=\"padding-bottom: 2rem;\">\n  <div class=\"paragraph\">Probably because of all the Plump Squirrels I've been feeding.</div>\n</div>\n<div class=\"section avoid-break-inside\" style=\"padding-bottom: 2rem;\">\n  <div class=\"paragraph\">Dammit.</div>\n</div>",
  "text": "The birds are going wild outside my window.\nProbably because of all the Plump Squirrels I've been feeding.\nDammit.",
  "images": [],
  "links": []
}