[
  {
    "title": "UNIX",
    "url": "https://www.youtube.com/watch?v=tc4ROCJYbm0",
    "hostname": "www.youtube.com"
  },
  {
    "title": "HyperCard",
    "url": "https://www.youtube.com/watch?v=FquNpWdf9vg",
    "hostname": "www.youtube.com"
  },
  {
    "title": "Inform 7",
    "url": "https://www.youtube.com/watch?v=bTdoFHTxQRI",
    "hostname": "www.youtube.com"
  },
  {
    "title": "WikiWikiWeb",
    "url": "https://www.youtube.com/watch?v=XqxwwuUdsp4",
    "hostname": "www.youtube.com"
  },
  {
    "title": "Siri",
    "url": "https://www.youtube.com/watch?v=pjdBEg5T11w",
    "hostname": "www.youtube.com"
  },
  {
    "title": "Visual Programming Languages",
    "url": "https://www.youtube.com/watch?v=cAiFJEcqwm4",
    "hostname": "www.youtube.com"
  },
  {
    "title": "Infographics",
    "url": "https://www.youtube.com/watch?v=5Zg-C8AAIGg",
    "hostname": "www.youtube.com"
  },
  {
    "title": "Dashboards",
    "url": "https://www.youtube.com/watch?v=pV8-e_P7NWQ",
    "hostname": "www.youtube.com"
  },
  {
    "title": "old adventure games",
    "url": "https://www.youtube.com/watch?v=gKlZzAWIlJc",
    "hostname": "www.youtube.com"
  }
]