[
  {
    "title": "Evidence Of Exceptional Ability",
    "url": "https://www.youtube.com/watch?v=Io3sdAAcZLw",
    "hostname": "www.youtube.com"
  },
  {
    "title": "Independent Entrepreneur",
    "url": "https://www.youtube.com/watch?v=ZoqgAy3h4OM",
    "hostname": "www.youtube.com"
  },
  {
    "title": "colleges will line up to take the maximum possible amount of not just the money you have, but also the maximum amount of money you can borrow",
    "url": "https://www.youtube.com/watch?v=pUanS5OWy_k",
    "hostname": "www.youtube.com"
  }
]