[
  {
    "title": "hackers have access to a detailed map of your home",
    "url": "https://youtu.be/uhyM-bhzFsI?t=674",
    "hostname": "youtu.be"
  },
  {
    "title": "yeoman templates",
    "url": "https://yeoman.io/authoring/",
    "hostname": "yeoman.io"
  },
  {
    "title": "example of a confusing adapter in Rete.js",
    "url": "https://rete.js.org/#/docs/controls",
    "hostname": "rete.js.org"
  },
  {
    "title": "A really neat example of pretty code, is Dream Code",
    "url": "https://nobackend.org/dreamcode.html",
    "hostname": "nobackend.org"
  },
  {
    "title": "but the world took a completely different path than this creating even more complexity",
    "url": "https://www.youtube.com/watch?v=TRKRg1O3H0s",
    "hostname": "www.youtube.com"
  },
  {
    "title": "Rete.js",
    "url": "https://rete.js.org/#/examples/basic",
    "hostname": "rete.js.org"
  },
  {
    "title": "Dataflow",
    "url": "https://jerosoler.github.io/Drawflow/",
    "hostname": "jerosoler.github.io"
  },
  {
    "title": "Cytoscape.js",
    "url": "https://js.cytoscape.org/",
    "hostname": "js.cytoscape.org"
  }
]