[
  {
    "title": "lemon",
    "url": "https://www.youtube.com/watch?v=5Hh6uHUx728",
    "hostname": "www.youtube.com"
  },
  {
    "title": "teachers doing as little as possible to just get paid",
    "url": "https://www.youtube.com/watch?v=8jsUj4DqWfU",
    "hostname": "www.youtube.com"
  },
  {
    "title": "purposefully manipulating your grades",
    "url": "https://www.youtube.com/watch?v=DzSnvxejenY",
    "hostname": "www.youtube.com"
  },
  {
    "title": "it is a sign of getting indoctrinated into a fantasy lifestyle",
    "url": "https://www.youtube.com/watch?v=8ve23i5K334",
    "hostname": "www.youtube.com"
  },
  {
    "title": "Mimicry is actually normal part of early human development",
    "url": "https://en.wikipedia.org/wiki/Loevinger%27s_stages_of_ego_development",
    "hostname": "en.wikipedia.org"
  },
  {
    "title": "it becomes a component in a process of indoctrination",
    "url": "https://www.youtube.com/watch?v=IzZh2wstj88",
    "hostname": "www.youtube.com"
  },
  {
    "title": "often do not awaken from their bad judgment until they face some life threatening illness",
    "url": "https://www.youtube.com/watch?v=hPSvdKTEZug",
    "hostname": "www.youtube.com"
  },
  {
    "title": "few will ever learn to see outside of themselves",
    "url": "https://www.youtube.com/watch?v=bVV2Zk88beY",
    "hostname": "www.youtube.com"
  },
  {
    "title": "if those tests were real all the students would fail them today",
    "url": "https://www.youtube.com/watch?v=8ve23i5K334",
    "hostname": "www.youtube.com"
  },
  {
    "title": "People with the fraudulent diplomas and now student debt",
    "url": "https://www.youtube.com/watch?v=8ve23i5K334",
    "hostname": "www.youtube.com"
  },
  {
    "title": "they will not understand you, they gave up on understanding",
    "url": "https://www.youtube.com/watch?v=8jsUj4DqWfU",
    "hostname": "www.youtube.com"
  },
  {
    "title": "aim to become an independent business person",
    "url": "https://www.youtube.com/watch?v=ZoqgAy3h4OM",
    "hostname": "www.youtube.com"
  },
  {
    "title": "Learn lmms",
    "url": "https://www.youtube.com/watch?v=0sRvkaxh8EU",
    "hostname": "www.youtube.com"
  },
  {
    "title": "Use a projector",
    "url": "https://www.youtube.com/watch?v=BXW0xgYNxlc",
    "hostname": "www.youtube.com"
  },
  {
    "title": "the little master painting techniques",
    "url": "https://www.youtube.com/watch?v=NK4Uo5QvH6M",
    "hostname": "www.youtube.com"
  },
  {
    "title": "get a cheap 3D printer",
    "url": "https://www.youtube.com/watch?v=gokN9xNG94U",
    "hostname": "www.youtube.com"
  },
  {
    "title": "learn 3D modeling",
    "url": "https://www.youtube.com/watch?v=TPrnSACiTJ4",
    "hostname": "www.youtube.com"
  },
  {
    "title": "The real trap of poverty, is a regular job that will destroy your mental health",
    "url": "https://www.youtube.com/watch?v=hPSvdKTEZug",
    "hostname": "www.youtube.com"
  },
  {
    "title": "that kind of thing will only result the principal calling them a lemon and having them do a little dance for failure to teach",
    "url": "https://www.youtube.com/watch?v=5Hh6uHUx728",
    "hostname": "www.youtube.com"
  }
]